README.txt
setup.py
collective/__init__.py
collective.colorbox.egg-info/PKG-INFO
collective.colorbox.egg-info/SOURCES.txt
collective.colorbox.egg-info/dependency_links.txt
collective.colorbox.egg-info/entry_points.txt
collective.colorbox.egg-info/namespace_packages.txt
collective.colorbox.egg-info/not-zip-safe
collective.colorbox.egg-info/paster_plugins.txt
collective.colorbox.egg-info/requires.txt
collective.colorbox.egg-info/top_level.txt
collective/colorbox/__init__.py
collective/colorbox/configure.zcml
collective/colorbox/tests.py
collective/colorbox/browser/__init__.py
collective/colorbox/browser/configure.zcml
collective/colorbox/browser/demo.pt
collective/colorbox/browser/flash.pt
collective/colorbox/browser/jquery.colorbox.css
collective/colorbox/browser/jquery.colorbox.demo.js
collective/colorbox/browser/jquery.colorbox.js
collective/colorbox/browser/images/border.png
collective/colorbox/browser/images/controls.png
collective/colorbox/browser/images/loading.gif
collective/colorbox/browser/images/loading_background.png
collective/colorbox/browser/images/overlay.png
collective/colorbox/browser/images/internet_explorer/borderBottomCenter.png
collective/colorbox/browser/images/internet_explorer/borderBottomLeft.png
collective/colorbox/browser/images/internet_explorer/borderBottomRight.png
collective/colorbox/browser/images/internet_explorer/borderMiddleLeft.png
collective/colorbox/browser/images/internet_explorer/borderMiddleRight.png
collective/colorbox/browser/images/internet_explorer/borderTopCenter.png
collective/colorbox/browser/images/internet_explorer/borderTopLeft.png
collective/colorbox/browser/images/internet_explorer/borderTopRight.png
collective/colorbox/profiles/default/cssregistry.xml
collective/colorbox/profiles/default/jsregistry.xml
collective/colorbox/profiles/default/metadata.xml
docs/HISTORY.txt
docs/INSTALL.txt
docs/LICENSE.GPL
docs/LICENSE.txt