Metadata-Version: 1.0
Name: collective.colorbox
Version: 0.1.6rc2
Summary: A jQuery plugin that provides lightboxes in Plone
Home-page: http://plone.org/products/collective.colorbox
Author: David Bain
Author-email: pigeonflight@gmail.com
License: GPL
Keywords: plone slideshow lightbox jquery colorbox
Platform: UNKNOWN
Classifier: Framework :: Plone
Classifier: Programming Language :: Python
Classifier: Programming Language :: JavaScript
Classifier: Development Status :: 4 - Beta
Classifier: Topic :: Software Development :: User Interfaces
